edms_client_api/__init__.py
edms_client_api/api_client.py
edms_client_api/api_response.py
edms_client_api/configuration.py
edms_client_api/exceptions.py
edms_client_api/py.typed
edms_client_api/rest.py
edms_client_api/api/__init__.py
edms_client_api/api/metadata_api.py
edms_client_api/api/time_series_api.py
edms_client_api/models/__init__.py
edms_client_api/models/aggregation_type.py
edms_client_api/models/commodity_type.py
edms_client_api/models/data_type.py
edms_client_api/models/data_value_type.py
edms_client_api/models/dataset_configuration_dto.py
edms_client_api/models/dataset_metadata_column_dto.py
edms_client_api/models/dataset_metadata_dto.py
edms_client_api/models/gps_point_dto.py
edms_client_api/models/granularity_unit.py
edms_client_api/models/http_validation_problem_details.py
edms_client_api/models/place_category.py
edms_client_api/models/place_dto.py
edms_client_api/models/place_type.py
edms_client_api/models/problem_details.py
edms_client_api/models/scope.py
edms_client_api/models/time_zone.py
edms_client_api/models/unit_denominator.py
edms_client_api/models/unit_numerator.py
edms_client_api/models/validation_problem_details.py
edms_client_api-1.1.0.post1.dist-info/METADATA
edms_client_api-1.1.0.post1.dist-info/WHEEL
edms_client_api-1.1.0.post1.dist-info/top_level.txt
edms_client_api-1.1.0.post1.dist-info/RECORD
