Metadata-Version: 2.1
Name: edms-client-api
Version: 1.1.0.post1
Summary: EDMS Client Api
Home-page: UNKNOWN
Author: OpenAPI Generator community
Author-email: team@openapitools.org
License: UNKNOWN
Keywords: OpenAPI,OpenAPI-Generator,EDMS Client Api
Platform: UNKNOWN
Requires-Dist: urllib3 (<3.0.0,>=2.1.0)
Requires-Dist: python-dateutil (>=2.8.2)
Requires-Dist: pydantic (>=2)
Requires-Dist: typing-extensions (>=4.7.1)
